{"final_sfen": "3+N1G+P2/+B+P2R1+S2/+L+P1+PpP1+Pl/K1p2+P+PL1/1Pg4pb/4+n1p2/1p+s2+p+nk1/2+p+pr1+n1+p/2+s1g1sg1 b l 321", "moves": [{"usi": "6i6h", "score": null}, {"usi": "3a4b", "score": null}, {"usi": "2h1h", "score": null}, {"usi": "8b6b", "score": null}, {"usi": "5i6i", "score": null}, {"usi": "6a5b", "score": null}, {"usi": "9i9h", "score": null}, {"usi": "4b3a", "score": null}, {"usi": "4i5i", "score": null}, {"usi": "7c7d", "score": null}, {"usi": "9g9f", "score": null}, {"usi": "6b6a", "score": null}, {"usi": "5i4i", "score": null}, {"usi": "5c5d", "score": null}, {"usi": "9f9e", "score": null}, {"usi": "4a4b", "score": null}, {"usi": "3i3h", "score": -3.143749952316284, "unknown_abs": 0}, {"usi": "7a6b", "score": -2.94384765625, "unknown_abs": 0}, {"usi": "4i3i", "score": -3.5843749046325684, "unknown_abs": 0}, {"usi": "4b5c", "score": -3.017871141433716, "unknown_abs": 0}, {"usi": "6i7h", "score": -2.9212889671325684, "unknown_abs": 0}, {"usi": "8c8d", "score": -3.0648436546325684, "unknown_abs": 0}, {"usi": "8g8f", "score": -2.9102540016174316, "unknown_abs": 0}, {"usi": "4c4d", "score": -2.8070311546325684, "unknown_abs": 0}, {"usi": "8f8e", "score": -3.4300780296325684, "unknown_abs": 0}, {"usi": "4d4e", "score": -2.856152296066284, "unknown_abs": 0}, {"usi": "7h8g", "score": -2.7818360328674316, "unknown_abs": 0}, {"usi": "6b7c", "score": -3.322070360183716, "unknown_abs": 0}, {"usi": "8e8d", "score": -2.491992235183716, "unknown_abs": 0}, {"usi": "3c3d", "score": -3.0596680641174316, "unknown_abs": 0}, {"usi": "3g3f", "score": -3.110644578933716, "unknown_abs": 0}, {"usi": "3d3e", "score": -3.5508790016174316, "unknown_abs": 1}, {"usi": "8h9i", "score": -3.384570360183716, "unknown_abs": 0}, {"usi": "1c1d", "score": -3.2564454078674316, "unknown_abs": 1}, {"usi": "4g4f", "score": -3.4896483421325684, "unknown_abs": 0}, {"usi": "9c9d", "score": -3.658007860183716, "unknown_abs": 1}, {"usi": "5g5f", "score": -3.310546875, "unknown_abs": 0}, {"usi": "4e4f", "score": -3.1982421875, "unknown_abs": 1}, {"usi": "8g7f", "score": -3.752734422683716, "unknown_abs": 0}, {"usi": "4f4g+", "score": -3.800976514816284, "unknown_abs": 1}, {"usi": "3i2h", "score": -3.9749999046325684, "unknown_abs": 0}, {"usi": "9d9e", "score": -3.5853514671325684, "unknown_abs": 1}, {"usi": "2g2f", "score": -3.516406297683716, "unknown_abs": 0}, {"usi": "7c6d", "score": -3.2369141578674316, "unknown_abs": 1}, {"usi": "5f5e", "score": -3.961132764816284, "unknown_abs": 0}, {"usi": "2b3c", "score": -3.727734327316284, "unknown_abs": 0}, {"usi": "P*9c", "score": -4.122265815734863, "unknown_abs": 0}, {"usi": "8a7c", "score": -3.646484375, "unknown_abs": 0}, {"usi": "3h2g", "score": -3.075976610183716, "unknown_abs": 0}, {"usi": "6a6b", "score": -4.026171684265137, "unknown_abs": 0}, {"usi": "2h3h", "score": -3.7333984375, "unknown_abs": 0}, {"usi": "7c8e", "score": -4.012499809265137, "unknown_abs": 0}, {"usi": "7i7h", "score": -3.337890625, "unknown_abs": 0}, {"usi": "1d1e", "score": -3.943164110183716, "unknown_abs": 0}, {"usi": "3h4g", "score": -2.6353516578674316, "unknown_abs": 0}, {"usi": "5a4b", "score": -3.937695264816284, "unknown_abs": 0}, {"usi": "3f3e", "score": -3.265429735183716, "unknown_abs": 0}, {"usi": "6d5e", "score": -3.890625, "unknown_abs": 0}, {"usi": "7h8g", "score": -3.6396484375, "unknown_abs": 0}, {"usi": "2c2d", "score": -4.175000190734863, "unknown_abs": 0}, {"usi": "6h7h", "score": -3.696484327316284, "unknown_abs": 0}, {"usi": "4b4c", "score": -3.804882764816284, "unknown_abs": 0}, {"usi": "4g5f", "score": -3.815234422683716, "unknown_abs": 0}, {"usi": "7d7e", "score": -3.7783203125, "unknown_abs": 0}, {"usi": "7f7e", "score": -1.08740234375, "unknown_abs": 0}, {"usi": "6c6d", "score": -3.9248046875, "unknown_abs": 0}, {"usi": "P*4g", "score": -3.868359327316284, "unknown_abs": 0}, {"usi": "3a4b", "score": -3.9632811546325684, "unknown_abs": 0}, {"usi": "5f6f", "score": -3.128124952316284, "unknown_abs": 0}, {"usi": "1e1f", "score": -4.032812595367432, "unknown_abs": 0}, {"usi": "3e3d", "score": -3.427929639816284, "unknown_abs": 0}, {"usi": "4c3d", "score": -3.323535203933716, "unknown_abs": 0}, {"usi": "6f5f", "score": -3.6253905296325684, "unknown_abs": 0}, {"usi": "3d3e", "score": -3.81640625, "unknown_abs": 0}, {"usi": "6g6f", "score": -3.686718702316284, "unknown_abs": 0}, {"usi": "5b4c", "score": -4.354296684265137, "unknown_abs": 0}, {"usi": "2g3f", "score": -3.5374999046325684, "unknown_abs": 0}, {"usi": "3e3d", "score": -1.920312523841858, "unknown_abs": 0}, {"usi": "2i3g", "score": -3.8335938453674316, "unknown_abs": 0}, {"usi": "6b7b", "score": -3.86376953125, "unknown_abs": 0}, {"usi": "7e8e", "score": -0.47285154461860657, "unknown_abs": 0}, {"usi": "P*3e", "score": -3.5645508766174316, "unknown_abs": 1}, {"usi": "8g8f", "score": -4.177929878234863, "unknown_abs": 0}, {"usi": "5c4d", "score": -3.551464796066284, "unknown_abs": 1}, {"usi": "3g4e", "score": -3.851269483566284, "unknown_abs": 0}, {"usi": "3e3f", "score": -3.0586915016174316, "unknown_abs": 1}, {"usi": "9h9g", "score": -3.9019532203674316, "unknown_abs": 0}, {"usi": "1f1g+", "score": -3.5576171875, "unknown_abs": 1}, {"usi": "4e3c+", "score": -3.4144530296325684, "unknown_abs": 0}, {"usi": "2a3c", "score": -1.5167968273162842, "unknown_abs": 0}, {"usi": "6f6e", "score": -3.5390625, "unknown_abs": 0}, {"usi": "P*4f", "score": -4.132616996765137, "unknown_abs": 1}, {"usi": "6e6d", "score": -3.280078172683716, "unknown_abs": 0}, {"usi": "3f3g+", "score": -3.8750977516174316, "unknown_abs": 1}, {"usi": "5f4f", "score": -3.3714842796325684, "unknown_abs": 0}, {"usi": "7b7a", "score": -3.88232421875, "unknown_abs": 1}, {"usi": "4f5e", "score": -3.791308641433716, "unknown_abs": 0}, {"usi": "4b5c", "score": -3.7255859375, "unknown_abs": 1}, {"usi": "5e5d", "score": -3.10302734375, "unknown_abs": 0}, {"usi": "4d5d", "score": -3.539257764816284, "unknown_abs": 1}, {"usi": "4g4f", "score": -4.001172065734863, "unknown_abs": 0}, {"usi": "2d2e", "score": -4.033300876617432, "unknown_abs": 1}, {"usi": "P*1c", "score": -3.974902391433716, "unknown_abs": 0}, {"usi": "P*6b", "score": -4.121679782867432, "unknown_abs": 1}, {"usi": "S*8c", "score": -3.805957078933716, "unknown_abs": 0}, {"usi": "2e2f", "score": -3.3946290016174316, "unknown_abs": 1}, {"usi": "7h6g", "score": -3.803027391433716, "unknown_abs": 0}, {"usi": "5d5e", "score": -3.79248046875, "unknown_abs": 1}, {"usi": "8c7d+", "score": -3.5604491233825684, "unknown_abs": 0}, {"usi": "P*4d", "score": -4.376172065734863, "unknown_abs": 0}, {"usi": "7g7f", "score": -3.407421827316284, "unknown_abs": 0}, {"usi": "9e9f", "score": -4.084374904632568, "unknown_abs": 0}, {"usi": "6g6h", "score": -3.491992235183716, "unknown_abs": 0}, {"usi": "N*3e", "score": -4.575781345367432, "unknown_abs": 0}, {"usi": "4f4e", "score": -3.845410108566284, "unknown_abs": 0}, {"usi": "1g1h", "score": -4.687890529632568, "unknown_abs": 0}, {"usi": "B*6a", "score": -3.7759766578674316, "unknown_abs": 0}, {"usi": "3g4g", "score": -4.672070503234863, "unknown_abs": 2}, {"usi": "7f7e", "score": -3.3916015625, "unknown_abs": 0}, {"usi": "3c4e", "score": -3.603515625, "unknown_abs": 2}, {"usi": "N*2e", "score": -3.81884765625, "unknown_abs": 0}, {"usi": "7a7d", "score": -4.4326171875, "unknown_abs": 2}, {"usi": "1i1h", "score": -3.430468797683716, "unknown_abs": 0}, {"usi": "7d8d", "score": -3.708203077316284, "unknown_abs": 3}, {"usi": "8e7f", "score": -1.110742211341858, "unknown_abs": 0}, {"usi": "4g3g", "score": -4.167578220367432, "unknown_abs": 3}, {"usi": "8f7g", "score": -3.664843797683716, "unknown_abs": 0}, {"usi": "P*8g", "score": -4.316015720367432, "unknown_abs": 3}, {"usi": "6a5b+", "score": -3.7242188453674316, "unknown_abs": 0}, {"usi": "P*5f", "score": -4.223242282867432, "unknown_abs": 3}, {"usi": "7e7d", "score": -3.7831053733825684, "unknown_abs": 0}, {"usi": "2f2g+", "score": -3.4189453125, "unknown_abs": 3}, {"usi": "P*8e", "score": -3.1214842796325684, "unknown_abs": 0}, {"usi": "8d8a", "score": -3.886914014816284, "unknown_abs": 3}, {"usi": "5b5a", "score": -3.2860350608825684, "unknown_abs": 0}, {"usi": "5c6d", "score": -4.249804496765137, "unknown_abs": 3}, {"usi": "7f8g", "score": -3.6539063453674316, "unknown_abs": 0}, {"usi": "3d2e", "score": -3.477343797683716, "unknown_abs": 3}, {"usi": "8g9h", "score": -4.1904296875, "unknown_abs": 0}, {"usi": "5f5g+", "score": -3.606250047683716, "unknown_abs": 3}, {"usi": "6h5g", "score": -3.579296827316284, "unknown_abs": 0}, {"usi": "2e2f", "score": -3.4051756858825684, "unknown_abs": 3}, {"usi": "P*5h", "score": -4.447851657867432, "unknown_abs": 0}, {"usi": "4c5c", "score": -3.8477540016174316, "unknown_abs": 3}, {"usi": "7d7c", "score": -4.441796779632568, "unknown_abs": 0}, {"usi": "6d7e", "score": -3.7464842796325684, "unknown_abs": 3}, {"usi": "5g4g", "score": -4.107031345367432, "unknown_abs": 0}, {"usi": "R*4i", "score": -3.50146484375, "unknown_abs": 3}, {"usi": "9g9f", "score": -3.51953125, "unknown_abs": 0}, {"usi": "5e6f", "score": -3.4619140625, "unknown_abs": 1}, {"usi": "7g8h", "score": -3.9124999046325684, "unknown_abs": 0}, {"usi": "G*3h", "score": -3.3919920921325684, "unknown_abs": 1}, {"usi": "5a4a", "score": -4.483788967132568, "unknown_abs": 0}, {"usi": "N*7f", "score": -3.5482420921325684, "unknown_abs": 0}, {"usi": "4g4f", "score": -4.321484565734863, "unknown_abs": 0}, {"usi": "4i4h", "score": -3.512988328933716, "unknown_abs": 0}, {"usi": "4f5e", "score": -4.012890815734863, "unknown_abs": 0}, {"usi": "P*3f", "score": -3.517578125, "unknown_abs": 0}, {"usi": "5e6d", "score": -4.086718559265137, "unknown_abs": 0}, {"usi": "P*8g", "score": -3.307421922683716, "unknown_abs": 0}, {"usi": "9h9g", "score": -3.7339844703674316, "unknown_abs": 0}, {"usi": "8g8h+", "score": -2.4990234375, "unknown_abs": 0}, {"usi": "P*4i", "score": -4.264062404632568, "unknown_abs": 0}, {"usi": "4h4i", "score": -2.8837890625, "unknown_abs": 0}, {"usi": "8i7g", "score": -3.760546922683716, "unknown_abs": 0}, {"usi": "5c5b", "score": -3.3080077171325684, "unknown_abs": 0}, {"usi": "P*4c", "score": -4.276757717132568, "unknown_abs": 0}, {"usi": "6b6c", "score": -3.253124952316284, "unknown_abs": 0}, {"usi": "4a5b", "score": -4.096875190734863, "unknown_abs": 0}, {"usi": "3g4g", "score": -3.427050828933716, "unknown_abs": 0}, {"usi": "P*6h", "score": -4.469922065734863, "unknown_abs": 0}, {"usi": "P*7h", "score": -3.5374999046325684, "unknown_abs": 0}, {"usi": "G*4b", "score": -4.418359279632568, "unknown_abs": 0}, {"usi": "S*6g", "score": -3.6455078125, "unknown_abs": 0}, {"usi": "5b6c", "score": -3.970507860183716, "unknown_abs": 0}, {"usi": "6g6h", "score": -2.6919922828674316, "unknown_abs": 0}, {"usi": "P*2d", "score": -4.325390815734863, "unknown_abs": 0}, {"usi": "4e3g+", "score": -3.6412110328674316, "unknown_abs": 0}, {"usi": "6d5d", "score": -3.8984375, "unknown_abs": 0}, {"usi": "S*3i", "score": -3.7314453125, "unknown_abs": 0}, {"usi": "9f9e", "score": -4.015820503234863, "unknown_abs": 0}, {"usi": "6h6i+", "score": -3.6834959983825684, "unknown_abs": 0}, {"usi": "6c7b", "score": -3.8578124046325684, "unknown_abs": 0}, {"usi": "8a7a", "score": -3.100781202316284, "unknown_abs": 0}, {"usi": "P*6d", "score": -4.223437309265137, "unknown_abs": 0}, {"usi": "7h7i+", "score": -3.600390672683716, "unknown_abs": 0}, {"usi": "7b7a", "score": -3.8082032203674316, "unknown_abs": 0}, {"usi": "P*9d", "score": -3.5374999046325684, "unknown_abs": 0}, {"usi": "9i8h", "score": -4.118359565734863, "unknown_abs": 1}, {"usi": "4i4h", "score": -3.522656202316284, "unknown_abs": 0}, {"usi": "7a8a", "score": -4.411328315734863, "unknown_abs": 1}, {"usi": "S*6g", "score": -3.739941358566284, "unknown_abs": 0}, {"usi": "2d2c+", "score": -4.10546875, "unknown_abs": 1}, {"usi": "6g7h+", "score": -3.4789061546325684, "unknown_abs": 0}, {"usi": "5d5e", "score": -4.490624904632568, "unknown_abs": 1}, {"usi": "7h7g", "score": -3.578125, "unknown_abs": 0}, {"usi": "9e9d", "score": -3.4019532203674316, "unknown_abs": 1}, {"usi": "P*8g", "score": -3.379589796066284, "unknown_abs": 0}, {"usi": "P*3d", "score": -4.561913967132568, "unknown_abs": 2}, {"usi": "7i7h", "score": -3.443359375, "unknown_abs": 0}, {"usi": "5e4e", "score": -4.598046779632568, "unknown_abs": 2}, {"usi": "4d4e", "score": -2.6434569358825684, "unknown_abs": 0}, {"usi": "R*8b", "score": -4.692578315734863, "unknown_abs": 2}, {"usi": "G*4i", "score": -3.0218749046325684, "unknown_abs": 1}, {"usi": "8e8d", "score": -3.998046875, "unknown_abs": 0}, {"usi": "7e8d", "score": -3.4208984375, "unknown_abs": 0}, {"usi": "8b7b", "score": -3.9214844703674316, "unknown_abs": 0}, {"usi": "P*6g", "score": -3.644335985183716, "unknown_abs": 0}, {"usi": "3d3c+", "score": -4.296288967132568, "unknown_abs": 0}, {"usi": "8d7e", "score": -2.78955078125, "unknown_abs": 0}, {"usi": "2c2d", "score": -4.32421875, "unknown_abs": 0}, {"usi": "7h7i", "score": -3.2767577171325684, "unknown_abs": 0}, {"usi": "P*8c", "score": -4.463086128234863, "unknown_abs": 0}, {"usi": "3h2h", "score": -2.7958984375, "unknown_abs": 0}, {"usi": "P*2b", "score": -4.375390529632568, "unknown_abs": 0}, {"usi": "4g5h", "score": -2.8296875953674316, "unknown_abs": 0}, {"usi": "9c9b+", "score": -4.296875, "unknown_abs": 0}, {"usi": "P*5a", "score": -3.40625, "unknown_abs": 0}, {"usi": "7b8b", "score": -4.591406345367432, "unknown_abs": 0}, {"usi": "N*5e", "score": -3.5726561546325684, "unknown_abs": 0}, {"usi": "P*5i", "score": -4.556054592132568, "unknown_abs": 0}, {"usi": "2g1h", "score": -3.160937547683716, "unknown_abs": 0}, {"usi": "8h7i", "score": -2.564453125, "unknown_abs": 0}, {"usi": "7f6h+", "score": -3.584277391433716, "unknown_abs": 0}, {"usi": "9g9f", "score": -3.012011766433716, "unknown_abs": 0}, {"usi": "2f2g", "score": -3.4580078125, "unknown_abs": 0}, {"usi": "8b7b", "score": -3.5482420921325684, "unknown_abs": 0}, {"usi": "5e4g+", "score": -3.37060546875, "unknown_abs": 0}, {"usi": "7i6h", "score": -2.994921922683716, "unknown_abs": 0}, {"usi": "7e7f", "score": -2.675488233566284, "unknown_abs": 0}, {"usi": "N*5d", "score": -4.384179592132568, "unknown_abs": 0}, {"usi": "4e4f", "score": -3.0829100608825684, "unknown_abs": 0}, {"usi": "2d3d", "score": -3.9951171875, "unknown_abs": 0}, {"usi": "2h2i", "score": -3.173144578933716, "unknown_abs": 0}, {"usi": "6h7g", "score": -2.5703125, "unknown_abs": 0}, {"usi": "4g3h", "score": -3.534374952316284, "unknown_abs": 0}, {"usi": "3d3e", "score": -3.992968797683716, "unknown_abs": 0}, {"usi": "7f7g+", "score": -2.1009764671325684, "unknown_abs": 0}, {"usi": "S*3a", "score": -3.6041016578674316, "unknown_abs": 0}, {"usi": "5a5b", "score": -3.085253953933716, "unknown_abs": 0}, {"usi": "2b2a+", "score": -3.7353515625, "unknown_abs": 0}, {"usi": "4f4g+", "score": -3.3890624046325684, "unknown_abs": 0}, {"usi": "9f9e", "score": -3.0254883766174316, "unknown_abs": 0}, {"usi": "6i7i", "score": -3.5263671875, "unknown_abs": 0}, {"usi": "N*6h", "score": -3.716796875, "unknown_abs": 0}, {"usi": "B*5g", "score": -3.482226610183716, "unknown_abs": 0}, {"usi": "3c3d", "score": -3.4325194358825684, "unknown_abs": 0}, {"usi": "5h6i", "score": -3.439648389816284, "unknown_abs": 0}, {"usi": "3a2b+", "score": -3.4791016578674316, "unknown_abs": 0}, {"usi": "6g6h+", "score": -2.8271484375, "unknown_abs": 0}, {"usi": "P*2e", "score": -3.5794920921325684, "unknown_abs": 0}, {"usi": "N*6e", "score": -3.50439453125, "unknown_abs": 0}, {"usi": "2b3a", "score": -3.258593797683716, "unknown_abs": 0}, {"usi": "9a9b", "score": -3.054492235183716, "unknown_abs": 0}, {"usi": "2a2b", "score": -3.074511766433716, "unknown_abs": 0}, {"usi": "P*6a", "score": -3.3814454078674316, "unknown_abs": 0}, {"usi": "8a9b", "score": -3.363476514816284, "unknown_abs": 0}, {"usi": "4h5h", "score": -3.509765625, "unknown_abs": 0}, {"usi": "3a2a", "score": -3.586621046066284, "unknown_abs": 0}, {"usi": "4i5i", "score": -3.209179639816284, "unknown_abs": 0}, {"usi": "2a3a", "score": -3.421093702316284, "unknown_abs": 0}, {"usi": "P*7d", "score": -3.6292967796325684, "unknown_abs": 0}, {"usi": "L*2d", "score": -3.8062500953674316, "unknown_abs": 0}, {"usi": "6a6b", "score": -3.34130859375, "unknown_abs": 0}, {"usi": "8c8b+", "score": -3.4188475608825684, "unknown_abs": 0}, {"usi": "7i7h", "score": -3.556347608566284, "unknown_abs": 0}, {"usi": "5d6b+", "score": -3.30859375, "unknown_abs": 0}, {"usi": "6h6g", "score": -3.2723631858825684, "unknown_abs": 0}, {"usi": "P*8e", "score": -3.673144578933716, "unknown_abs": 0}, {"usi": "3h4h", "score": -3.58154296875, "unknown_abs": 0}, {"usi": "6b6a", "score": -2.7540040016174316, "unknown_abs": 0}, {"usi": "2g3h", "score": -3.669238328933716, "unknown_abs": 0}, {"usi": "3e4e", "score": -3.321972608566284, "unknown_abs": 0}, {"usi": "7h8i", "score": -3.33984375, "unknown_abs": 0}, {"usi": "7b6b", "score": -2.760546922683716, "unknown_abs": 0}, {"usi": "5b5c", "score": -3.301074266433716, "unknown_abs": 1}, {"usi": "2b2a", "score": -3.26025390625, "unknown_abs": 0}, {"usi": "2i1i", "score": -3.7490234375, "unknown_abs": 1}, {"usi": "7c7b+", "score": -3.241015672683716, "unknown_abs": 0}, {"usi": "3h2h", "score": -3.763671875, "unknown_abs": 1}, {"usi": "4e5e", "score": -3.450000047683716, "unknown_abs": 0}, {"usi": "6i6h", "score": -3.5201172828674316, "unknown_abs": 1}, {"usi": "6b5b", "score": -3.6810545921325684, "unknown_abs": 0}, {"usi": "1i2i", "score": -3.4754881858825684, "unknown_abs": 0}, {"usi": "5e4e", "score": -3.917675733566284, "unknown_abs": 0}, {"usi": "2h3h", "score": -3.2060546875, "unknown_abs": 0}, {"usi": "8b8c", "score": -3.842968702316284, "unknown_abs": 0}, {"usi": "6h7h", "score": -3.55517578125, "unknown_abs": 0}, {"usi": "9d9c+", "score": -3.3169922828674316, "unknown_abs": 0}, {"usi": "7h8h", "score": -4.0771484375, "unknown_abs": 0}, {"usi": "9e8d", "score": -3.119140625, "unknown_abs": 0}, {"usi": "L*4a", "score": -4.541406154632568, "unknown_abs": 0}, {"usi": "4e4d", "score": -3.085742235183716, "unknown_abs": 0}, {"usi": "8h7h", "score": -4.056445121765137, "unknown_abs": 0}, {"usi": "4b3b", "score": -2.528515577316284, "unknown_abs": 0}, {"usi": "5g2d", "score": -4.421484470367432, "unknown_abs": 0}, {"usi": "8d9d", "score": -3.313183546066284, "unknown_abs": 0}, {"usi": "8i7i", "score": -4.592577934265137, "unknown_abs": 0}, {"usi": "6d6c+", "score": -3.41748046875, "unknown_abs": 0}, {"usi": "2d1e", "score": -3.8125, "unknown_abs": 0}, {"usi": "3b4a", "score": -3.8287110328674316, "unknown_abs": 0}, {"usi": "1a1c", "score": -4.476953029632568, "unknown_abs": 0}, {"usi": "3a3b", "score": -3.799023389816284, "unknown_abs": 1}, {"usi": "3h2h", "score": -4.353320121765137, "unknown_abs": 0}, {"usi": "2e2d", "score": -3.9839844703674316, "unknown_abs": 0}, {"usi": "6g6h", "score": -4.629492282867432, "unknown_abs": 0}, {"usi": "2a2b", "score": -3.9691405296325684, "unknown_abs": 0}, {"usi": "P*2e", "score": -4.491015434265137, "unknown_abs": 0}, {"usi": "4a4b", "score": -3.945507764816284, "unknown_abs": 0}, {"usi": "6f7f", "score": -4.4951171875, "unknown_abs": 0}, {"usi": "2b3a", "score": -3.54443359375, "unknown_abs": 0}, {"usi": "4h3h", "score": -4.406445503234863, "unknown_abs": 0}, {"usi": "2d2c+", "score": -3.5743165016174316, "unknown_abs": 0}, {"usi": "6e5g+", "score": -4.467187404632568, "unknown_abs": 0}, {"usi": "7b8b", "score": -3.8531250953674316, "unknown_abs": 0}, {"usi": "5g5f", "score": -4.593554496765137, "unknown_abs": 0}, {"usi": "L*2d", "score": -4.214257717132568, "unknown_abs": 0}, {"usi": "7f7e", "score": -4.581445217132568, "unknown_abs": 0}, {"usi": "4b4a", "score": -3.55029296875, "unknown_abs": 0}, {"usi": "2h2g", "score": -4.742578029632568, "unknown_abs": 0}], "plies": 320, "stop_reason": "max_plies"}